patchmentation/__init__.py
patchmentation/patchmentation.py
patchmentation/collections/__init__.py
patchmentation/collections/bbox.py
patchmentation/collections/dataset.py
patchmentation/collections/image.py
patchmentation/collections/image_patch.py
patchmentation/collections/mask.py
patchmentation/collections/patch.py
patchmentation/data/__init__.py
patchmentation/data/campus.py
patchmentation/data/data.py
patchmentation/data/datautils.py
patchmentation/data/pascal_voc_2007.py
patchmentation/data/penn_fudan_ped.py
patchmentation/utils/__init__.py
patchmentation/utils/comparator.py
patchmentation/utils/converter.py
patchmentation/utils/filter.py
patchmentation/utils/functional.py
patchmentation/utils/loader.py
patchmentation/utils/transform.py
patchmentation-0.1.16.dist-info/LICENSE
patchmentation-0.1.16.dist-info/METADATA
patchmentation-0.1.16.dist-info/WHEEL
patchmentation-0.1.16.dist-info/top_level.txt
patchmentation-0.1.16.dist-info/RECORD
